Seance/Explainer.py
Seance/Forecaster.py
Seance/Optimizer.py
Seance/__init__.py
Seance/Builder/PanelAxis.py
Seance/Builder/PreProcess.py
Seance/Builder/Transformations.py
Seance/Builder/__init__.py
Seance/basis_functions/__init__.py
Seance/basis_functions/fourier_basis.py
Seance/basis_functions/linear_basis.py
Seance-0.1.4.dist-info/LICENSE
Seance-0.1.4.dist-info/METADATA
Seance-0.1.4.dist-info/WHEEL
Seance-0.1.4.dist-info/top_level.txt
Seance-0.1.4.dist-info/RECORD
