Metadata-Version: 2.1
Name: Seance
Version: 0.1.4
Summary: A Wrapper around MLForecast.
Home-page: https://github.com/tblume1992/Seance
Author: Tyler Blume
Author-email: t-blume@hotmail.com
Keywords: forecasting,time series,lightgbm,mlforecast
Classifier: Programming Language :: Python :: 3
Classifier: License :: OSI Approved :: MIT License
Classifier: Operating System :: OS Independent
License-File: LICENSE
Requires-Dist: numpy
Requires-Dist: pandas
Requires-Dist: optuna
Requires-Dist: mlforecast (==0.7.0)
Requires-Dist: lightgbm
Requires-Dist: catboost
Requires-Dist: xgboost
